PaoniuSanshiliuji/README.md
PaoniuSanshiliuji/__init__.py
PaoniuSanshiliuji/__main__.py
PaoniuSanshiliuji/file.epub
PaoniuSanshiliuji/index.html
PaoniuSanshiliuji/css/__init__.py
PaoniuSanshiliuji/css/annotations.css
PaoniuSanshiliuji/css/main.css
PaoniuSanshiliuji/css/normalize.css
PaoniuSanshiliuji/css/popup.css
PaoniuSanshiliuji/font/__init__.py
PaoniuSanshiliuji/font/fontello.eot
PaoniuSanshiliuji/font/fontello.svg
PaoniuSanshiliuji/font/fontello.ttf
PaoniuSanshiliuji/font/fontello.woff
PaoniuSanshiliuji/img/__init__.py
PaoniuSanshiliuji/img/annotator-glyph-sprite.png
PaoniuSanshiliuji/img/annotator-icon-sprite.png
PaoniuSanshiliuji/img/apple-touch-icon.png
PaoniuSanshiliuji/img/cancelfullscreen.png
PaoniuSanshiliuji/img/close.png
PaoniuSanshiliuji/img/fullscreen.png
PaoniuSanshiliuji/img/loader.gif
PaoniuSanshiliuji/img/menu-icon.png
PaoniuSanshiliuji/img/save.png
PaoniuSanshiliuji/img/saved.png
PaoniuSanshiliuji/img/settings-s.png
PaoniuSanshiliuji/img/settings.png
PaoniuSanshiliuji/img/star.png
PaoniuSanshiliuji/js/__init__.py
PaoniuSanshiliuji/js/epub.js
PaoniuSanshiliuji/js/epub.min.js
PaoniuSanshiliuji/js/epub.min.map
PaoniuSanshiliuji/js/hooks.min.js
PaoniuSanshiliuji/js/hooks.min.map
PaoniuSanshiliuji/js/reader.js
PaoniuSanshiliuji/js/reader.js.map
PaoniuSanshiliuji/js/reader.min.js
PaoniuSanshiliuji/js/reader.min.map
PaoniuSanshiliuji/js/hooks/__init__.py
PaoniuSanshiliuji/js/hooks/extensions/__init__.py
PaoniuSanshiliuji/js/hooks/extensions/highlight.js
PaoniuSanshiliuji/js/libs/__init__.py
PaoniuSanshiliuji/js/libs/jquery.min.js
PaoniuSanshiliuji/js/libs/localforage.min.js
PaoniuSanshiliuji/js/libs/screenfull.js
PaoniuSanshiliuji/js/libs/screenfull.min.js
PaoniuSanshiliuji/js/libs/zip.min.js
PaoniuSanshiliuji/js/plugins/__init__.py
PaoniuSanshiliuji/js/plugins/hypothesis.js
PaoniuSanshiliuji/js/plugins/search.js
paoniu_sanshiliuji-2022.10.11.0.dist-info/METADATA
paoniu_sanshiliuji-2022.10.11.0.dist-info/WHEEL
paoniu_sanshiliuji-2022.10.11.0.dist-info/entry_points.txt
paoniu_sanshiliuji-2022.10.11.0.dist-info/top_level.txt
paoniu_sanshiliuji-2022.10.11.0.dist-info/RECORD
